pyseapc/ExternalPythonInterface_pb2.py
pyseapc/ExternalPythonInterface_pb2_grpc.py
pyseapc/__init__.py
pyseapc/server.py
pyseapc-0.0.4.dist-info/METADATA
pyseapc-0.0.4.dist-info/WHEEL
pyseapc-0.0.4.dist-info/top_level.txt
pyseapc-0.0.4.dist-info/RECORD
