Metadata-Version: 2.4
Name: pyseapc
Version: 0.0.4
Summary: SE APC external Python interface
Author-email: SE_APC <global.apc.support@se.com>
License-Expression: MIT
Classifier: Programming Language :: Python :: 3
Classifier: Operating System :: OS Independent
Requires-Python: >=3.9
Requires-Dist: grpcio>=1.73.1
Requires-Dist: grpcio-tools>=1.73.1
Requires-Dist: pyOpenSSL>=25.1.0
